gateoverflow/__init__.py
gateoverflow/__main__.py
gateoverflow/actions.py
gateoverflow/constants.py
gateoverflow/default_config.toml
gateoverflow/helpers.py
gateoverflow/logger.py
gateoverflow/opengate.py
gateoverflow/queries.py
gateoverflow/state.py
gateoverflow-0.5.3.dist-info/LICENSE
gateoverflow-0.5.3.dist-info/METADATA
gateoverflow-0.5.3.dist-info/WHEEL
gateoverflow-0.5.3.dist-info/entry_points.txt
gateoverflow-0.5.3.dist-info/top_level.txt
gateoverflow-0.5.3.dist-info/RECORD
