Metadata-Version: 2.1
Name: gateoverflow
Version: 0.5.3
Summary: A command line interface for gateoverflow links
Home-page: https://github.com/toxdes/opengate
Author: Vaibhav Mali
Author-email: malivp3494@gmail.com
License: UNKNOWN
Platform: UNKNOWN
Classifier: Programming Language :: Python :: 3
Classifier: License :: OSI Approved :: MIT License
Classifier: Operating System :: OS Independent
Requires-Python: >=3.6
Requires-Dist: tabulate
Requires-Dist: python-dateutil
Requires-Dist: requests
Requires-Dist: toml (>=0.10)
